vaknl_image/__init__.py
vaknl_image/Image/__init__.py
vaknl_image-1.3.1.dist-info/LICENSE
vaknl_image-1.3.1.dist-info/METADATA
vaknl_image-1.3.1.dist-info/WHEEL
vaknl_image-1.3.1.dist-info/top_level.txt
vaknl_image-1.3.1.dist-info/RECORD
